{"253000": {"count": 1}, "1721YY": {"count": 1}, "252030": {"count": 1}, "211010": {"count": 1}, "353031": {"count": 1}, "291060": {"count": 1}, "419020": {"count": 1}, "132011": {"count": 1}, "131111": {"count": 1}, "412031": {"count": 1}, "251000": {"count": 2}, "252020": {"count": 2}, "119021": {"count": 1}, "413099": {"count": 2}, "431011": {"count": 1}, "119XXX": {"count": 2}, "339021": {"count": 1}, "211020": {"count": 2}, "272012": {"count": 1}, "count": 85, "291123": {"count": 1}, "111021": {"count": 1}, "119141": {"count": 1}, "151199": {"count": 1}, "113031": {"count": 1}, "151150": {"count": 1}, "491011": {"count": 1}, "4990XX": {"count": 1}, "1110XX": {"count": 2}, "131199": {"count": 1}, "N.A.//": {"count": 47}, "131070": {"count": 1}, "414010": {"count": 2}}