{"272020": {"count": 2}, "537062": {"count": 1}, "419091": {"count": 1}, "339030": {"count": 1}, "492011": {"count": 1}, "472031": {"count": 2}, "537064": {"count": 1}, "47207X": {"count": 2}, "435081": {"count": 4}, "412031": {"count": 2}, "N.A.//": {"count": 86}, "272099": {"count": 1}, "119021": {"count": 1}, "453000": {"count": 6}, "393090": {"count": 2}, "119XXX": {"count": 1}, "count": 133, "119051": {"count": 1}, "999920": {"count": 1}, "37201X": {"count": 3}, "434051": {"count": 1}, "373010": {"count": 3}, "33909X": {"count": 1}, "533030": {"count": 2}, "352010": {"count": 2}, "535020": {"count": 1}, "472061": {"count": 2}, "352021": {"count": 2}}