{"272020": {"count": 5}, "131070": {"count": 14}, "435053": {"count": 1}, "1110XX": {"count": 12}, "519111": {"count": 1}, "371012": {"count": 3}, "452011": {"count": 1}, "435030": {"count": 5}, "119151": {"count": 6}, "519061": {"count": 12}, "172011": {"count": 2}, "532020": {"count": 1}, "273031": {"count": 3}, "537064": {"count": 3}, "113021": {"count": 12}, "439022": {"count": 4}, "435021": {"count": 1}, "552010": {"count": 5}, "331011": {"count": 3}, "151143": {"count": 6}, "472111": {"count": 4}, "131041": {"count": 2}, "536021": {"count": 1}, "113031": {"count": 25}, "131161": {"count": 3}, "232011": {"count": 4}, "4990XX": {"count": 3}, "113011": {"count": 1}, "399021": {"count": 3}, "518021": {"count": 1}, "537070": {"count": 1}, "359021": {"count": 1}, "292050": {"count": 1}, "333050": {"count": 23}, "132070": {"count": 8}, "472XXX": {"count": 1}, "131151": {"count": 4}, "519010": {"count": 1}, "5191XX": {"count": 10}, "559830": {"count": 10}, "132081": {"count": 1}, "439011": {"count": 3}, "131199": {"count": 4}, "394031": {"count": 1}, "413031": {"count": 6}, "532031": {"count": 1}, "131051": {"count": 2}, "119021": {"count": 3}, "119XXX": {"count": 44}, "113071": {"count": 4}, "439051": {"count": 1}, "292081": {"count": 1}, "151121": {"count": 17}, "29112X": {"count": 2}, "119013": {"count": 1}, "272040": {"count": 5}, "259041": {"count": 6}, "393021": {"count": 1}, "413041": {"count": 1}, "172131": {"count": 1}, "499091": {"count": 1}, "353011": {"count": 1}, "433099": {"count": 2}, "193011": {"count": 1}, "391021": {"count": 2}, "353031": {"count": 2}, "119051": {"count": 12}, "112011": {"count": 1}, "132051": {"count": 1}, "419041": {"count": 2}, "291051": {"count": 9}, "292021": {"count": 2}, "119041": {"count": 6}, "273020": {"count": 1}, "435071": {"count": 6}, "419031": {"count": 1}, "372021": {"count": 2}, "511011": {"count": 20}, "471011": {"count": 3}, "331012": {"count": 2}, "434171": {"count": 1}, "435051": {"count": 4}, "493023": {"count": 7}, "339093": {"count": 3}, "271010": {"count": 2}, "299000": {"count": 1}, "172110": {"count": 2}, "291122": {"count": 1}, "516011": {"count": 1}, "2590XX": {"count": 1}, "534010": {"count": 1}, "392021": {"count": 1}, "518010": {"count": 1}, "435111": {"count": 1}, "439061": {"count": 2}, "47207X": {"count": 2}, "419091": {"count": 1}, "193030": {"count": 1}, "131030": {"count": 10}, "211020": {"count": 20}, "537051": {"count": 5}, "292061": {"count": 1}, "291126": {"count": 4}, "192030": {"count": 2}, "435081": {"count": 18}, "514XXX": {"count": 3}, "531000": {"count": 4}, "251000": {"count": 12}, "999920": {"count": 4}, "171010": {"count": 2}, "413011": {"count": 3}, "399011": {"count": 8}, "1940YY": {"count": 1}, "5340XX": {"count": 1}, "113121": {"count": 10}, "551010": {"count": 1}, "499071": {"count": 3}, "351012": {"count": 1}, "351011": {"count": 1}, "332011": {"count": 7}, "194031": {"count": 2}, "192040": {"count": 2}, "434051": {"count": 21}, "333010": {"count": 13}, "492097": {"count": 3}, "291071": {"count": 5}, "333021": {"count": 5}, "274021": {"count": 1}, "472140": {"count": 2}, "132021": {"count": 5}, "1720XX": {"count": 1}, "173020": {"count": 8}, "439041": {"count": 3}, "493031": {"count": 2}, "49904X": {"count": 2}, "15113X": {"count": 24}, "492098": {"count": 1}, "291141": {"count": 22}, "434111": {"count": 2}, "433011": {"count": 3}, "532010": {"count": 5}, "131022": {"count": 4}, "292041": {"count": 2}, "493021": {"count": 1}, "312020": {"count": 1}, "434071": {"count": 2}, "419020": {"count": 7}, "492011": {"count": 5}, "519194": {"count": 1}, "432021": {"count": 2}, "292030": {"count": 4}, "131111": {"count": 17}, "412031": {"count": 45}, "499021": {"count": 4}, "112020": {"count": 14}, "413021": {"count": 12}, "252030": {"count": 35}, "413099": {"count": 14}, "434081": {"count": 1}, "273010": {"count": 1}, "393090": {"count": 2}, "434061": {"count": 2}, "533099": {"count": 1}, "4750YY": {"count": 1}, "37201X": {"count": 18}, "4750XX": {"count": 1}, "113061": {"count": 2}, "119141": {"count": 3}, "151199": {"count": 6}, "131141": {"count": 1}, "339030": {"count": 33}, "274030": {"count": 2}, "472031": {"count": 2}, "131023": {"count": 6}, "5370XX": {"count": 1}, "472061": {"count": 7}, "253000": {"count": 14}, "1721YY": {"count": 22}, "514041": {"count": 2}, "434131": {"count": 1}, "211010": {"count": 4}, "131121": {"count": 6}, "339091": {"count": 3}, "412010": {"count": 14}, "172041": {"count": 7}, "151141": {"count": 2}, "254021": {"count": 1}, "537061": {"count": 2}, "292090": {"count": 1}, "512031": {"count": 1}, "292010": {"count": 8}, "21109X": {"count": 1}, "331099": {"count": 2}, "433061": {"count": 2}, "172051": {"count": 8}, "count": 3952, "254010": {"count": 1}, "518031": {"count": 2}, "433021": {"count": 1}, "434181": {"count": 4}, "212011": {"count": 14}, "491011": {"count": 3}, "536031": {"count": 1}, "132011": {"count": 53}, "435052": {"count": 4}, "516021": {"count": 1}, "339011": {"count": 1}, "271020": {"count": 10}, "1910XX": {"count": 1}, "151131": {"count": 12}, "131081": {"count": 4}, "1940XX": {"count": 3}, "492020": {"count": 3}, "273041": {"count": 1}, "152031": {"count": 1}, "291060": {"count": 2}, "311010": {"count": 12}, "252010": {"count": 3}, "537062": {"count": 21}, "431011": {"count": 32}, "436010": {"count": 4}, "113051": {"count": 4}, "272099": {"count": 1}, "291127": {"count": 1}, "533030": {"count": 43}, "193051": {"count": 1}, "119111": {"count": 9}, "291031": {"count": 1}, "132052": {"count": 6}, "519151": {"count": 2}, "132099": {"count": 1}, "272012": {"count": 3}, "192099": {"count": 3}, "171020": {"count": 1}, "319092": {"count": 2}, "111021": {"count": 14}, "439XXX": {"count": 4}, "252020": {"count": 76}, "512090": {"count": 7}, "173010": {"count": 1}, "353021": {"count": 1}, "2740XX": {"count": 2}, "439021": {"count": 1}, "411011": {"count": 31}, "232090": {"count": 1}, "151134": {"count": 5}, "252050": {"count": 2}, "414010": {"count": 18}, "132053": {"count": 2}, "419099": {"count": 3}, "474011": {"count": 2}, "452041": {"count": 1}, "411012": {"count": 18}, "273042": {"count": 1}, "151150": {"count": 16}, "553010": {"count": 2}, "352010": {"count": 4}, "211092": {"count": 20}, "172070": {"count": 6}, "172141": {"count": 7}, "472150": {"count": 1}, "533041": {"count": 12}, "291124": {"count": 3}, "N.A.//": {"count": 2296}, "352021": {"count": 1}, "359031": {"count": 1}, "151122": {"count": 4}, "5350XX": {"count": 1}, "434XXX": {"count": 1}, "339021": {"count": 4}, "151142": {"count": 9}, "1721XX": {"count": 4}, "396010": {"count": 3}, "119030": {"count": 9}, "371011": {"count": 4}, "493011": {"count": 1}, "113131": {"count": 1}, "399030": {"count": 10}, "373010": {"count": 5}, "518090": {"count": 3}, "395011": {"count": 2}, "433031": {"count": 9}, "132082": {"count": 7}, "533020": {"count": 7}, "514120": {"count": 1}}