{"119151": {"count": 1}, "391021": {"count": 1}, "435053": {"count": 1}, "353031": {"count": 3}, "311010": {"count": 4}, "519111": {"count": 3}, "411012": {"count": 1}, "514041": {"count": 1}, "537081": {"count": 1}, "413011": {"count": 1}, "412031": {"count": 3}, "533030": {"count": 12}, "353041": {"count": 1}, "131070": {"count": 1}, "435071": {"count": 3}, "512090": {"count": 1}, "471011": {"count": 2}, "536021": {"count": 1}, "511011": {"count": 2}, "472130": {"count": 2}, "434171": {"count": 3}, "493023": {"count": 6}, "533011": {"count": 1}, "372012": {"count": 2}, "396010": {"count": 1}, "353021": {"count": 1}, "472031": {"count": 2}, "534010": {"count": 1}, "353022": {"count": 1}, "113071": {"count": 1}, "472061": {"count": 9}, "513093": {"count": 1}, "435111": {"count": 1}, "3590XX": {"count": 1}, "537062": {"count": 7}, "472080": {"count": 1}, "414010": {"count": 2}, "211010": {"count": 1}, "count": 454, "339091": {"count": 1}, "5191XX": {"count": 5}, "537051": {"count": 5}, "339030": {"count": 7}, "537064": {"count": 4}, "519020": {"count": 1}, "537061": {"count": 3}, "514XXX": {"count": 2}, "533041": {"count": 1}, "N.A.//": {"count": 258}, "352021": {"count": 4}, "472181": {"count": 1}, "371011": {"count": 1}, "512031": {"count": 1}, "119051": {"count": 1}, "435081": {"count": 3}, "537030": {"count": 1}, "999920": {"count": 24}, "4520XX": {"count": 1}, "351011": {"count": 1}, "472040": {"count": 1}, "439051": {"count": 1}, "319092": {"count": 1}, "151199": {"count": 1}, "439011": {"count": 1}, "412010": {"count": 4}, "37201X": {"count": 9}, "373010": {"count": 3}, "33909X": {"count": 1}, "512020": {"count": 1}, "433031": {"count": 1}, "472140": {"count": 1}, "533020": {"count": 7}, "359021": {"count": 5}, "399021": {"count": 1}, "352010": {"count": 2}, "251000": {"count": 1}, "454020": {"count": 1}}