{"439051": {"count": 1}, "131070": {"count": 1}, "119141": {"count": 1}, "1110XX": {"count": 1}, "517041": {"count": 1}, "112011": {"count": 1}, "412010": {"count": 4}, "452011": {"count": 1}, "412031": {"count": 1}, "533030": {"count": 5}, "453000": {"count": 1}, "471011": {"count": 1}, "435021": {"count": 1}, "331012": {"count": 1}, "999920": {"count": 2}, "111021": {"count": 2}, "472111": {"count": 1}, "113031": {"count": 2}, "499098": {"count": 1}, "472031": {"count": 2}, "411011": {"count": 1}, "N.A.//": {"count": 106}, "472061": {"count": 2}, "359021": {"count": 1}, "253000": {"count": 1}, "3590XX": {"count": 1}, "519071": {"count": 1}, "411012": {"count": 1}, "211010": {"count": 1}, "339030": {"count": 2}, "5191XX": {"count": 1}, "559830": {"count": 2}, "454011": {"count": 2}, "131051": {"count": 1}, "435081": {"count": 2}, "472150": {"count": 1}, "119030": {"count": 1}, "352021": {"count": 1}, "518031": {"count": 1}, "1940YY": {"count": 1}, "47XXXX": {"count": 1}, "4520XX": {"count": 1}, "count": 181, "332011": {"count": 2}, "119051": {"count": 1}, "434031": {"count": 1}, "434051": {"count": 1}, "391010": {"count": 1}, "514120": {"count": 1}, "373010": {"count": 1}, "119013": {"count": 2}, "352010": {"count": 2}, "49904X": {"count": 1}, "393010": {"count": 1}, "519111": {"count": 1}, "311010": {"count": 1}, "439041": {"count": 1}, "434111": {"count": 1}}