{"493031": {"count": 1}, "514041": {"count": 1}, "434XXX": {"count": 1}, "353031": {"count": 1}, "419020": {"count": 1}, "537051": {"count": 1}, "292061": {"count": 1}, "537064": {"count": 2}, "435081": {"count": 1}, "533041": {"count": 1}, "395090": {"count": 1}, "N.A.//": {"count": 34}, "491011": {"count": 1}, "count": 59, "111021": {"count": 1}, "472111": {"count": 1}, "151199": {"count": 1}, "433031": {"count": 1}, "434051": {"count": 1}, "173020": {"count": 1}, "439061": {"count": 1}, "411011": {"count": 1}, "553010": {"count": 3}, "359021": {"count": 1}}