{"272020": {"count": 2}, "532010": {"count": 1}, "353031": {"count": 5}, "399021": {"count": 2}, "514041": {"count": 1}, "131111": {"count": 1}, "412031": {"count": 3}, "399041": {"count": 2}, "119021": {"count": 1}, "533030": {"count": 9}, "435071": {"count": 2}, "351011": {"count": 1}, "512090": {"count": 1}, "49904X": {"count": 1}, "372012": {"count": 2}, "511011": {"count": 2}, "999920": {"count": 3}, "516011": {"count": 1}, "472111": {"count": 2}, "439XXX": {"count": 1}, "113011": {"count": 1}, "311010": {"count": 2}, "439021": {"count": 1}, "411011": {"count": 4}, "419099": {"count": 1}, "499043": {"count": 1}, "472061": {"count": 3}, "359021": {"count": 4}, "37201X": {"count": 6}, "253000": {"count": 1}, "3590XX": {"count": 1}, "47207X": {"count": 2}, "292061": {"count": 1}, "411012": {"count": 2}, "475021": {"count": 1}, "count": 284, "412010": {"count": 3}, "436010": {"count": 4}, "435021": {"count": 1}, "5340XX": {"count": 1}, "472150": {"count": 1}, "472031": {"count": 5}, "33909X": {"count": 4}, "15113X": {"count": 1}, "352021": {"count": 1}, "194031": {"count": 1}, "435081": {"count": 4}, "119XXX": {"count": 2}, "499071": {"count": 1}, "339030": {"count": 2}, "119051": {"count": 2}, "434051": {"count": 1}, "514120": {"count": 2}, "493023": {"count": 3}, "373010": {"count": 7}, "533041": {"count": 1}, "274021": {"count": 1}, "472140": {"count": 4}, "515111": {"count": 4}, "173020": {"count": 1}, "533020": {"count": 1}, "352010": {"count": 4}, "N.A.//": {"count": 145}, "435052": {"count": 1}, "291141": {"count": 1}, "1910XX": {"count": 1}}