{"333050": {"count": 1}, "1721YY": {"count": 1}, "292061": {"count": 1}, "339030": {"count": 1}, "412010": {"count": 1}, "559830": {"count": 1}, "291126": {"count": 1}, "292030": {"count": 1}, "435081": {"count": 1}, "292041": {"count": 1}, "N.A.//": {"count": 21}, "533030": {"count": 1}, "119XXX": {"count": 1}, "count": 44, "533099": {"count": 1}, "434051": {"count": 3}, "472111": {"count": 1}, "373010": {"count": 1}, "333021": {"count": 1}, "271010": {"count": 1}, "119081": {"count": 1}, "533020": {"count": 1}, "411011": {"count": 1}}