{"272020": {"count": 1}, "3590XX": {"count": 1}, "119151": {"count": 1}, "252050": {"count": 1}, "252010": {"count": 1}, "131161": {"count": 1}, "291051": {"count": 1}, "N.A.//": {"count": 47}, "113031": {"count": 3}, "436010": {"count": 5}, "171010": {"count": 1}, "413011": {"count": 1}, "119111": {"count": 1}, "211020": {"count": 1}, "count": 80, "111021": {"count": 1}, "151199": {"count": 1}, "252020": {"count": 4}, "132011": {"count": 4}, "251000": {"count": 1}, "271020": {"count": 1}, "414010": {"count": 2}}