{"131022": {"count": 1}, "119151": {"count": 1}, "399021": {"count": 1}, "2911XX": {"count": 7}, "292030": {"count": 1}, "131111": {"count": 2}, "435030": {"count": 1}, "412031": {"count": 4}, "119030": {"count": 5}, "413021": {"count": 1}, "419020": {"count": 7}, "273031": {"count": 1}, "372012": {"count": 1}, "399011": {"count": 2}, "112031": {"count": 1}, "113061": {"count": 2}, "113031": {"count": 4}, "232011": {"count": 2}, "113011": {"count": 1}, "1110XX": {"count": 3}, "333050": {"count": 1}, "291131": {"count": 13}, "211010": {"count": 3}, "419010": {"count": 1}, "252050": {"count": 1}, "519071": {"count": 1}, "254021": {"count": 1}, "352010": {"count": 2}, "532031": {"count": 1}, "292090": {"count": 2}, "292010": {"count": 1}, "331099": {"count": 2}, "119XXX": {"count": 3}, "4520XX": {"count": 1}, "count": 1004, "254010": {"count": 1}, "29112X": {"count": 1}, "212011": {"count": 2}, "291020": {"count": 6}, "193030": {"count": 3}, "132011": {"count": 12}, "2310XX": {"count": 104}, "271020": {"count": 5}, "439061": {"count": 2}, "151131": {"count": 1}, "253000": {"count": 1}, "319094": {"count": 1}, "252030": {"count": 4}, "119141": {"count": 1}, "291060": {"count": 47}, "311010": {"count": 3}, "434131": {"count": 1}, "431011": {"count": 1}, "291051": {"count": 14}, "119111": {"count": 5}, "193051": {"count": 1}, "533030": {"count": 1}, "274021": {"count": 1}, "273020": {"count": 1}, "132052": {"count": 2}, "211020": {"count": 2}, "192099": {"count": 3}, "999920": {"count": 2}, "291041": {"count": 4}, "319092": {"count": 1}, "111021": {"count": 1}, "231012": {"count": 2}, "252020": {"count": 22}, "291199": {"count": 3}, "131199": {"count": 1}, "411011": {"count": 3}, "291081": {"count": 1}, "353031": {"count": 1}, "436010": {"count": 2}, "411012": {"count": 3}, "131030": {"count": 2}, "292061": {"count": 1}, "291126": {"count": 1}, "131161": {"count": 1}, "395090": {"count": 1}, "251000": {"count": 11}, "171010": {"count": 1}, "113121": {"count": 2}, "291011": {"count": 5}, "434171": {"count": 1}, "291123": {"count": 4}, "434051": {"count": 1}, "113131": {"count": 1}, "399030": {"count": 2}, "273043": {"count": 1}, "433031": {"count": 1}, "132082": {"count": 1}, "1910XX": {"count": 1}, "131131": {"count": 1}, "N.A.//": {"count": 592}, "319011": {"count": 2}, "291141": {"count": 17}, "434111": {"count": 1}}