{"551010": {"count": 1}, "191010": {"count": 1}, "119151": {"count": 2}, "131070": {"count": 2}, "419020": {"count": 1}, "291011": {"count": 2}, "373010": {"count": 1}, "131111": {"count": 8}, "412031": {"count": 2}, "119030": {"count": 14}, "112020": {"count": 4}, "519061": {"count": 1}, "252030": {"count": 6}, "273031": {"count": 1}, "251000": {"count": 138}, "191020": {"count": 5}, "291071": {"count": 1}, "113061": {"count": 1}, "119141": {"count": 3}, "151199": {"count": 1}, "113031": {"count": 2}, "1520XX": {"count": 3}, "1930XX": {"count": 3}, "1110XX": {"count": 8}, "131023": {"count": 1}, "535020": {"count": 1}, "319091": {"count": 1}, "292050": {"count": 2}, "253000": {"count": 5}, "291131": {"count": 5}, "211010": {"count": 2}, "412010": {"count": 2}, "291181": {"count": 2}, "152031": {"count": 1}, "292010": {"count": 1}, "119XXX": {"count": 9}, "172051": {"count": 1}, "count": 1092, "254010": {"count": 1}, "29112X": {"count": 3}, "212011": {"count": 4}, "291020": {"count": 2}, "193030": {"count": 33}, "132011": {"count": 5}, "2310XX": {"count": 5}, "1910XX": {"count": 20}, "151131": {"count": 1}, "273041": {"count": 5}, "119121": {"count": 2}, "291060": {"count": 18}, "311010": {"count": 2}, "252010": {"count": 1}, "431011": {"count": 1}, "291051": {"count": 31}, "291127": {"count": 1}, "533030": {"count": 1}, "119111": {"count": 3}, "519151": {"count": 1}, "211020": {"count": 2}, "272012": {"count": 2}, "192099": {"count": 13}, "359031": {"count": 1}, "999920": {"count": 3}, "291041": {"count": 1}, "132082": {"count": 1}, "252020": {"count": 14}, "2590XX": {"count": 6}, "131199": {"count": 2}, "411011": {"count": 5}, "194021": {"count": 1}, "419099": {"count": 1}, "273042": {"count": 4}, "273043": {"count": 6}, "131030": {"count": 1}, "436010": {"count": 2}, "131161": {"count": 3}, "192030": {"count": 1}, "131041": {"count": 1}, "516050": {"count": 1}, "1940YY": {"count": 1}, "113121": {"count": 1}, "434171": {"count": 1}, "291123": {"count": 14}, "434051": {"count": 2}, "399030": {"count": 1}, "15113X": {"count": 2}, "433031": {"count": 1}, "111021": {"count": 2}, "439061": {"count": 2}, "N.A.//": {"count": 604}, "291141": {"count": 4}, "434111": {"count": 2}}