{"272020": {"count": 8}, "131070": {"count": 11}, "435053": {"count": 4}, "1110XX": {"count": 11}, "519111": {"count": 4}, "371012": {"count": 2}, "392011": {"count": 2}, "435030": {"count": 11}, "259041": {"count": 68}, "272011": {"count": 1}, "395090": {"count": 6}, "519061": {"count": 39}, "292021": {"count": 1}, "435071": {"count": 35}, "131121": {"count": 1}, "113021": {"count": 2}, "439022": {"count": 27}, "435021": {"count": 2}, "332020": {"count": 1}, "112031": {"count": 1}, "513092": {"count": 6}, "472111": {"count": 1}, "113031": {"count": 24}, "232011": {"count": 19}, "4990XX": {"count": 4}, "419020": {"count": 17}, "518021": {"count": 1}, "212021": {"count": 1}, "319091": {"count": 10}, "359021": {"count": 7}, "292050": {"count": 18}, "132070": {"count": 7}, "472XXX": {"count": 1}, "131151": {"count": 3}, "519010": {"count": 2}, "5191XX": {"count": 32}, "2911XX": {"count": 1}, "559830": {"count": 5}, "132081": {"count": 2}, "439011": {"count": 5}, "433051": {"count": 12}, "353031": {"count": 122}, "516063": {"count": 10}, "532031": {"count": 1}, "439081": {"count": 2}, "119021": {"count": 5}, "119XXX": {"count": 28}, "433021": {"count": 27}, "395012": {"count": 87}, "439051": {"count": 3}, "292081": {"count": 2}, "434031": {"count": 6}, "29112X": {"count": 1}, "515111": {"count": 2}, "536061": {"count": 1}, "272040": {"count": 4}, "392021": {"count": 14}, "439071": {"count": 3}, "413041": {"count": 3}, "519120": {"count": 2}, "2310XX": {"count": 1}, "499091": {"count": 2}, "353011": {"count": 16}, "439061": {"count": 88}, "517021": {"count": 1}, "37201X": {"count": 47}, "435061": {"count": 21}, "391021": {"count": 3}, "254031": {"count": 7}, "515112": {"count": 6}, "112011": {"count": 1}, "419041": {"count": 1}, "319097": {"count": 2}, "132099": {"count": 2}, "533030": {"count": 23}, "519030": {"count": 2}, "513020": {"count": 2}, "512041": {"count": 1}, "51609X": {"count": 1}, "372021": {"count": 2}, "511011": {"count": 9}, "513099": {"count": 1}, "331012": {"count": 1}, "434171": {"count": 108}, "435051": {"count": 5}, "493023": {"count": 3}, "339093": {"count": 3}, "173031": {"count": 1}, "172110": {"count": 1}, "519080": {"count": 3}, "232090": {"count": 7}, "394031": {"count": 1}, "151150": {"count": 5}, "131199": {"count": 7}, "353022": {"count": 12}, "435111": {"count": 1}, "3590XX": {"count": 9}, "273042": {"count": 1}, "419091": {"count": 19}, "132031": {"count": 2}, "131030": {"count": 7}, "537051": {"count": 3}, "292061": {"count": 21}, "291126": {"count": 3}, "131161": {"count": 1}, "435081": {"count": 55}, "514XXX": {"count": 17}, "212099": {"count": 3}, "33909X": {"count": 4}, "434011": {"count": 3}, "119030": {"count": 16}, "413011": {"count": 4}, "434061": {"count": 2}, "1940YY": {"count": 2}, "172141": {"count": 1}, "113121": {"count": 6}, "435052": {"count": 25}, "351012": {"count": 20}, "339030": {"count": 14}, "332011": {"count": 1}, "194031": {"count": 2}, "292071": {"count": 6}, "151199": {"count": 4}, "434051": {"count": 104}, "333010": {"count": 5}, "519041": {"count": 1}, "351011": {"count": 1}, "531000": {"count": 2}, "274021": {"count": 6}, "472140": {"count": 5}, "515113": {"count": 4}, "173020": {"count": 6}, "433099": {"count": 8}, "352010": {"count": 61}, "15113X": {"count": 4}, "5140XX": {"count": 1}, "493011": {"count": 1}, "2590XX": {"count": 1}, "433011": {"count": 9}, "532010": {"count": 1}, "131022": {"count": 7}, "119151": {"count": 4}, "312020": {"count": 2}, "434071": {"count": 17}, "399021": {"count": 44}, "492011": {"count": 1}, "432021": {"count": 5}, "292030": {"count": 6}, "131111": {"count": 8}, "513011": {"count": 14}, "412031": {"count": 139}, "399041": {"count": 1}, "112020": {"count": 8}, "413021": {"count": 21}, "413099": {"count": 7}, "273090": {"count": 2}, "434081": {"count": 7}, "372012": {"count": 64}, "399011": {"count": 63}, "499071": {"count": 2}, "291071": {"count": 1}, "113061": {"count": 2}, "152031": {"count": 1}, "533011": {"count": 1}, "131141": {"count": 1}, "111021": {"count": 18}, "339021": {"count": 2}, "211093": {"count": 2}, "131023": {"count": 14}, "391010": {"count": 1}, "472061": {"count": 7}, "253000": {"count": 22}, "1721YY": {"count": 1}, "514041": {"count": 2}, "434131": {"count": 7}, "211010": {"count": 4}, "419010": {"count": 3}, "339091": {"count": 2}, "412010": {"count": 214}, "252050": {"count": 1}, "472031": {"count": 1}, "254021": {"count": 2}, "519020": {"count": 1}, "434121": {"count": 4}, "519197": {"count": 3}, "514030": {"count": 1}, "292090": {"count": 2}, "513091": {"count": 1}, "292010": {"count": 2}, "21109X": {"count": 2}, "331099": {"count": 1}, "433061": {"count": 1}, "count": 9624, "254010": {"count": 1}, "435041": {"count": 2}, "119051": {"count": 34}, "514021": {"count": 1}, "434181": {"count": 5}, "212011": {"count": 1}, "352021": {"count": 18}, "512020": {"count": 8}, "119081": {"count": 6}, "491011": {"count": 2}, "434161": {"count": 7}, "132011": {"count": 12}, "393010": {"count": 1}, "412022": {"count": 3}, "151121": {"count": 3}, "271020": {"count": 8}, "439041": {"count": 18}, "131081": {"count": 2}, "1940XX": {"count": 2}, "492020": {"count": 3}, "434041": {"count": 6}, "516064": {"count": 6}, "119141": {"count": 19}, "292041": {"count": 4}, "311010": {"count": 58}, "252010": {"count": 20}, "537062": {"count": 24}, "431011": {"count": 50}, "319096": {"count": 3}, "113111": {"count": 1}, "436010": {"count": 334}, "319094": {"count": 5}, "353041": {"count": 3}, "119111": {"count": 8}, "291031": {"count": 3}, "512090": {"count": 31}, "519151": {"count": 2}, "211020": {"count": 2}, "471011": {"count": 2}, "271010": {"count": 2}, "999920": {"count": 30}, "516011": {"count": 3}, "132082": {"count": 3}, "291125": {"count": 1}, "439XXX": {"count": 22}, "252020": {"count": 1}, "132052": {"count": 2}, "353021": {"count": 11}, "439021": {"count": 21}, "411011": {"count": 137}, "113071": {"count": 2}, "513093": {"count": 1}, "414010": {"count": 23}, "132053": {"count": 7}, "419099": {"count": 7}, "132051": {"count": 1}, "411012": {"count": 13}, "434XXX": {"count": 10}, "537064": {"count": 19}, "553010": {"count": 12}, "49904X": {"count": 4}, "412021": {"count": 5}, "537061": {"count": 3}, "472150": {"count": 1}, "533041": {"count": 3}, "N.A.//": {"count": 5903}, "399099": {"count": 4}, "516050": {"count": 2}, "359031": {"count": 16}, "393090": {"count": 5}, "319095": {"count": 1}, "516031": {"count": 20}, "432011": {"count": 5}, "319011": {"count": 7}, "393031": {"count": 3}, "319092": {"count": 11}, "371011": {"count": 7}, "291141": {"count": 7}, "514120": {"count": 1}, "399030": {"count": 8}, "373010": {"count": 5}, "395011": {"count": 4}, "433031": {"count": 109}, "499044": {"count": 1}, "433071": {"count": 35}, "533020": {"count": 23}, "4520XX": {"count": 6}, "119013": {"count": 5}, "434111": {"count": 9}, "434199": {"count": 9}, "131051": {"count": 1}}