{"253000": {"count": 1}, "353031": {"count": 1}, "419010": {"count": 1}, "252010": {"count": 2}, "252030": {"count": 1}, "433021": {"count": 1}, "311010": {"count": 1}, "292061": {"count": 2}, "5371XX": {"count": 1}, "432021": {"count": 1}, "292030": {"count": 2}, "531000": {"count": 1}, "132011": {"count": 1}, "N.A.//": {"count": 85}, "352021": {"count": 2}, "436010": {"count": 3}, "519061": {"count": 2}, "393090": {"count": 1}, "5350XX": {"count": 1}, "512090": {"count": 2}, "339021": {"count": 1}, "999920": {"count": 2}, "count": 155, "399011": {"count": 2}, "292081": {"count": 1}, "37201X": {"count": 1}, "434051": {"count": 4}, "119XXX": {"count": 1}, "412010": {"count": 8}, "319092": {"count": 5}, "412031": {"count": 4}, "252020": {"count": 1}, "433031": {"count": 1}, "259041": {"count": 1}, "399021": {"count": 2}, "5191XX": {"count": 1}, "411011": {"count": 2}, "251000": {"count": 1}, "292050": {"count": 1}, "419020": {"count": 1}, "472061": {"count": 1}, "439061": {"count": 1}, "399030": {"count": 1}}