{"119151": {"count": 1}, "391021": {"count": 1}, "3590XX": {"count": 1}, "399021": {"count": 10}, "519111": {"count": 1}, "434131": {"count": 1}, "353041": {"count": 1}, "412031": {"count": 2}, "112020": {"count": 1}, "519061": {"count": 2}, "435071": {"count": 2}, "433031": {"count": 2}, "519030": {"count": 1}, "372012": {"count": 5}, "399011": {"count": 10}, "999920": {"count": 4}, "516011": {"count": 5}, "232011": {"count": 1}, "4990XX": {"count": 1}, "412010": {"count": 20}, "411011": {"count": 2}, "353022": {"count": 1}, "359021": {"count": 1}, "353031": {"count": 11}, "537062": {"count": 2}, "419091": {"count": 1}, "434XXX": {"count": 1}, "count": 344, "5191XX": {"count": 1}, "519071": {"count": 1}, "435081": {"count": 1}, "472150": {"count": 1}, "395090": {"count": 20}, "4520XX": {"count": 1}, "352021": {"count": 2}, "516031": {"count": 17}, "434171": {"count": 1}, "311010": {"count": 13}, "351011": {"count": 1}, "395012": {"count": 2}, "119051": {"count": 1}, "433021": {"count": 2}, "514120": {"count": 1}, "37201X": {"count": 5}, "131131": {"count": 1}, "N.A.//": {"count": 181}, "271020": {"count": 1}}