{"119151": {"count": 1}, "252030": {"count": 3}, "152031": {"count": 2}, "419020": {"count": 2}, "252010": {"count": 1}, "131111": {"count": 3}, "412031": {"count": 1}, "151121": {"count": 2}, "112020": {"count": 1}, "273041": {"count": 1}, "413099": {"count": 1}, "273031": {"count": 1}, "273020": {"count": 1}, "113021": {"count": 2}, "211020": {"count": 1}, "192099": {"count": 2}, "132031": {"count": 2}, "434171": {"count": 1}, "319092": {"count": 1}, "111021": {"count": 4}, "1520XX": {"count": 1}, "113031": {"count": 1}, "232011": {"count": 1}, "1110XX": {"count": 2}, "419099": {"count": 1}, "151142": {"count": 1}, "N.A.//": {"count": 115}, "252020": {"count": 13}, "253000": {"count": 2}, "1721YY": {"count": 1}, "119041": {"count": 1}, "273043": {"count": 1}, "211010": {"count": 1}, "339030": {"count": 1}, "412010": {"count": 1}, "292061": {"count": 1}, "434111": {"count": 1}, "552010": {"count": 1}, "212099": {"count": 1}, "15113X": {"count": 1}, "119XXX": {"count": 4}, "999920": {"count": 1}, "count": 212, "29112X": {"count": 3}, "113131": {"count": 1}, "131131": {"count": 1}, "132021": {"count": 1}, "193030": {"count": 1}, "132011": {"count": 4}, "119030": {"count": 3}, "131070": {"count": 3}, "439061": {"count": 1}, "251000": {"count": 8}}